kbnf-0.4.2.dist-info/METADATA
kbnf-0.4.2.dist-info/WHEEL
kbnf-0.4.2.dist-info/licenses/LICENSE
kbnf/__init__.py
kbnf/engine.py
kbnf/kbnf.abi3.so
kbnf/triton_logits_mask.py
kbnf-0.4.2.dist-info/RECORD
