Metadata-Version: 2.4
Name: kbnf
Version: 0.4.2
Classifier: Development Status :: 4 - Beta
Classifier: Intended Audience :: Developers
Classifier: Intended Audience :: Science/Research
Classifier: Operating System :: OS Independent
Classifier: Topic :: Scientific/Engineering :: Artificial Intelligence
Classifier: Topic :: Text Processing
Classifier: Programming Language :: Rust
Classifier: Programming Language :: Python :: Implementation :: CPython
Requires-Dist: numpy
Requires-Dist: torch ; extra == 'torch'
Requires-Dist: triton ; extra == 'efficient-logits-mask'
Provides-Extra: torch
Provides-Extra: efficient_logits_mask
License-File: LICENSE
Summary: A fast constrained decoding engine based on context free grammar.
Keywords: deep-learning,language-model,guided-generation,structured,constrained-decoding
Author: Xintong Sun <xs28@rice.edu>
Author-email: Xintong Sun <xs28@rice.edu>
License: MIT OR Apache-2.0
Requires-Python: >=3.7
Project-URL: Source Code, https://github.com/Dan-Wanna-M/kbnf
